img_g/__init__.py
img_g/gen.py
img_g/readme.md
img_g/rect.py
meterviewer-1.5.1.dist-info/METADATA
meterviewer-1.5.1.dist-info/WHEEL
meterviewer-1.5.1.dist-info/entry_points.txt
meterviewer/__init__.py
meterviewer/config.py
meterviewer/dataset.py
meterviewer/datasets/__init__.py
meterviewer/datasets/dataset.py
meterviewer/datasets/imgv.py
meterviewer/datasets/join.py
meterviewer/datasets/read/__init__.py
meterviewer/datasets/read/config.py
meterviewer/datasets/read/detection.py
meterviewer/datasets/read/single.py
meterviewer/datasets/read/times.py
meterviewer/datasets/read/types.py
meterviewer/datasets/v1/__init__.py
meterviewer/datasets/v1/dataset.py
meterviewer/datasets/v1/dataset_cls.py
meterviewer/datasets/v2/__init__.py
meterviewer/datasets/v2/dataset.py
meterviewer/datasets/view.py
meterviewer/fastview/home.py
meterviewer/fastview/pages/__init__.py
meterviewer/fastview/pages/cmp_.py
meterviewer/fastview/pages/copy_page.py
meterviewer/fastview/pages/example.py
meterviewer/fastview/pages/genpath.py
meterviewer/fastview/pages/resize_.py
meterviewer/fastview/pages/view_dataset.py
meterviewer/fastview/pages/view_single.py
meterviewer/files.py
meterviewer/func.py
meterviewer/generator/__init__.py
meterviewer/generator/base.py
meterviewer/generator/config.py
meterviewer/generator/db.py
meterviewer/generator/jsondb.py
meterviewer/generator/schema.py
meterviewer/generator/single.py
meterviewer/generator/temp.py
meterviewer/generator/total.py
meterviewer/img/__init__.py
meterviewer/img/cmp.py
meterviewer/img/colorstyle.py
meterviewer/img/crop.py
meterviewer/img/cut.py
meterviewer/img/draw.py
meterviewer/img/process.py
meterviewer/img/resize.py
meterviewer/img/validator.py
meterviewer/meterset.py
meterviewer/models/__init__.py
meterviewer/models/func.py
meterviewer/models/littledb.py
meterviewer/name.py
meterviewer/store.py
meterviewer/types.py
meterviewer/validator.py
meterviewer/values.py
meterviewer/views/__init__.py
meterviewer/views/disk_dataset.py
meterviewer/views/np_dataset.py
meterviewer/views/quick.py
tmd/README.md
tmd/__init__.py
tmd/dataset.py
tmd/requirements.txt
meterviewer-1.5.1.dist-info/RECORD
