Metadata-Version: 2.1
Name: meterviewer
Version: 1.5.1
Summary: Process meter-formatted dataset.
Author-Email: svtter <svtter@qq.com>
License: MIT
Requires-Python: <4.0,>=3.9
Requires-Dist: matplotlib>=3.8.4
Requires-Dist: numpy>=1.26.4
Requires-Dist: pandas>=2.2.2
Requires-Dist: pillow>=10.3.0
Requires-Dist: toml>=0.10.2
Requires-Dist: opencv-python>=4.9.0.80
Requires-Dist: sqlalchemy>=2.0.30
Requires-Dist: alembic>=1.13.1
Requires-Dist: tqdm>=4.66.4
Requires-Dist: loguru>=0.7.2
Requires-Dist: pydantic>=2.10.6
